name2nat/__init__.py
name2nat/best-model.pt
name2nat/name2nat.py
name2nat/name2nats.pkl
name2nat-0.5.1.dist-info/LICENSE
name2nat-0.5.1.dist-info/METADATA
name2nat-0.5.1.dist-info/WHEEL
name2nat-0.5.1.dist-info/top_level.txt
name2nat-0.5.1.dist-info/RECORD
