Metadata-Version: 2.1
Name: name2nat
Version: 0.5.1
Summary: Nationality Prediction from Name
Home-page: https://github.com/Kyubyong/name2nat
Author: Kyubyong Park
Author-email: kbpark.linguist@gmail.com
License: Apache License 2.0
Platform: UNKNOWN
Classifier: Development Status :: 5 - Production/Stable
Classifier: Intended Audience :: Developers
Classifier: Intended Audience :: Science/Research
Classifier: License :: OSI Approved :: Apache Software License
Classifier: Operating System :: OS Independent
Classifier: Programming Language :: Python :: 3
Classifier: Programming Language :: Python :: 3.6
Classifier: Programming Language :: Python :: 3.7
Requires-Python: >=3.6
Requires-Dist: flair
